simple_message_channels/__init__.py
simple_message_channels/smc.py
simple_message_channels-0.0.1a2.dist-info/LICENSE
simple_message_channels-0.0.1a2.dist-info/WHEEL
simple_message_channels-0.0.1a2.dist-info/METADATA
simple_message_channels-0.0.1a2.dist-info/RECORD
